pydkfuel/__init__.py
pydkfuel/consts.py
pydkfuel/exceptions.py
pydkfuel/helpers/__init__.py
pydkfuel/helpers/company_specific.py
pydkfuel/helpers/prices.py
pydkfuel/helpers/web_scrape.py
pydkfuel/providers/__init__.py
pydkfuel/providers/circlek/__init__.py
pydkfuel/providers/f24/__init__.py
pydkfuel/providers/oil/__init__.py
pydkfuel/providers/ok/__init__.py
pydkfuel-0.0.1b1.dist-info/LICENSE
pydkfuel-0.0.1b1.dist-info/METADATA
pydkfuel-0.0.1b1.dist-info/WHEEL
pydkfuel-0.0.1b1.dist-info/RECORD
