Metadata-Version: 2.3
Name: pydkfuel
Version: 0.0.1b1
Summary: A PyPI module for fetching fuel prices from Danish providers
License: MIT
Author: Malene Trab
Author-email: malene@trab.dk
Requires-Python: >=3.11,<4.0
Classifier: License :: OSI Approved :: MIT License
Classifier: Programming Language :: Python :: 3
Classifier: Programming Language :: Python :: 3.11
Classifier: Programming Language :: Python :: 3.12
Classifier: Programming Language :: Python :: 3.13
Requires-Dist: requests (>=2.32.0,<3.0.0)
